assistr/__init__.py
assistr/app_config.py
assistr/assistant.py
assistr/base.py
assistr/base_components.py
assistr/db_utils.py
assistr/models.py
assistr/utils.py
assistr/paneltools/__init__.py
assistr/paneltools/components.py
assistr/paneltools/main.py
assistr/paneltools/utils.py
assistr/paneltools/golden/__init__.py
configs/dev_config_echo.py
configs/dev_config_simplechat.py
examples/app.py
scripts/run_chat_workflow.py
scripts/sent_pipe.py
scripts/sentiment_bert.py
src/assistr/__init__.py
src/assistr/app_config.py
src/assistr/assistant.py
src/assistr/base.py
src/assistr/base_components.py
src/assistr/db_utils.py
src/assistr/models.py
src/assistr/utils.py
src/assistr/paneltools/__init__.py
src/assistr/paneltools/components.py
src/assistr/paneltools/main.py
src/assistr/paneltools/utils.py
src/assistr/paneltools/golden/__init__.py
src/assistr/paneltools/golden/golden.css
src/assistr/paneltools/golden/golden.html
tests/__init__.py
workflows/workflow_db.py
workflows/workflow_echo.py
workflows/workflow_simplechat.py
assistr-0.1.0.dist-info/METADATA
assistr-0.1.0.dist-info/WHEEL
assistr-0.1.0.dist-info/licenses/LICENSE
assistr-0.1.0.dist-info/RECORD
