Metadata-Version: 2.4
Name: assistr
Version: 0.1.0
Summary: A set of utilities for building LLM assistants
Author-email: Patrick Sulin <psulin@intersystems.com>
License-File: LICENSE
Requires-Dist: litellm==1.63.7
Requires-Dist: loguru==0.7.2
Requires-Dist: pydantic-settings>=2.2.1
Requires-Dist: pydantic>=2.3.0
Requires-Dist: python-dotenv==1.0.0
Requires-Dist: sqlalchemy-iris==0.12.0
Requires-Dist: sqlalchemy>=2.0
